llm_git_commit.py
llm_git_commit-0.1.5.dist-info/licenses/LICENSE
llm_git_commit-0.1.5.dist-info/METADATA
llm_git_commit-0.1.5.dist-info/WHEEL
llm_git_commit-0.1.5.dist-info/entry_points.txt
llm_git_commit-0.1.5.dist-info/top_level.txt
llm_git_commit-0.1.5.dist-info/RECORD
