Metadata-Version: 2.4
Name: llm-git-commit
Version: 0.1.5
Summary: LLM plugin to generate git commit messages and interactively commit.
Author-email: shamanic <shamanicbeatbox@gmail.com>
License: Apache-2.0
Project-URL: Homepage, https://github.com/shamanicarts/llm-git-commit
Project-URL: Issues, https://github.com/shamanicarts/llm-git-commit
Classifier: License :: OSI Approved :: Apache Software License
Requires-Python: >=3.8
License-File: LICENSE
Requires-Dist: llm
Requires-Dist: click
Requires-Dist: prompt-toolkit
Dynamic: license-file
